tests/__init__.py
tests/test_titanium_proto.py
titanium_proto/__init__.py
titanium_proto/titanium_proto.py
titanium_proto/src/__init__.py
titanium_proto/src/titanium_field.py
titanium_proto/src/titanium_file_gen.py
titanium_proto-0.2.0.dist-info/LICENSE
titanium_proto-0.2.0.dist-info/METADATA
titanium_proto-0.2.0.dist-info/WHEEL
titanium_proto-0.2.0.dist-info/entry_points.txt
titanium_proto-0.2.0.dist-info/top_level.txt
titanium_proto-0.2.0.dist-info/RECORD
